dynamic_pricing_anc/__init__.py
dynamic_pricing_anc/classes/CustomLossFunctionDynPricJointModel.py
dynamic_pricing_anc/classes/DynamicPricingIndividualModels.py
dynamic_pricing_anc/classes/DynamicPricingOfPrimaryAndAncillaryProduct.py
dynamic_pricing_anc/classes/MABextendedLinUCBClassifier.py
dynamic_pricing_anc/classes/MultipleAncillaryProductsLinearDemand.py
dynamic_pricing_anc/classes/MultipleAncillaryProductsNonlinearDemand.py
dynamic_pricing_anc/functions/dp_ind_models_print_plot.py
dynamic_pricing_anc/functions/wtp_and_pax_arrival_distributions.py
dynamic_pricing_anc/metrics/dp_offline_metrics.py
dynamic_pricing_anc/metrics/dp_uplift.py
dynamic_pricing_anc-0.0.1.dist-info/LICENSE
dynamic_pricing_anc-0.0.1.dist-info/METADATA
dynamic_pricing_anc-0.0.1.dist-info/WHEEL
dynamic_pricing_anc-0.0.1.dist-info/top_level.txt
dynamic_pricing_anc-0.0.1.dist-info/RECORD
